minidumpmcp/__init__.py
minidumpmcp/__main__.py
minidumpmcp/cli.py
minidumpmcp/client.py
minidumpmcp/exceptions.py
minidumpmcp/server.py
minidumpmcp/client_validators/__init__.py
minidumpmcp/client_validators/validators.py
minidumpmcp/config/__init__.py
minidumpmcp/config/client_settings.py
minidumpmcp/config/settings.py
minidumpmcp/prompts/__init__.py
minidumpmcp/prompts/analyze_crash_with_expertise.md
minidumpmcp/prompts/analyze_technical_details.md
minidumpmcp/prompts/crash_analysis_provider.py
minidumpmcp/prompts/symbol_preparation_provider.py
minidumpmcp/prompts/symbol_transformation_guide.md
minidumpmcp/resources/__init__.py
minidumpmcp/tools/__init__.py
minidumpmcp/tools/_common.py
minidumpmcp/tools/dump_syms.py
minidumpmcp/tools/stackwalk.py
minidumpmcp/tools/bin/dump-syms-linux
minidumpmcp/tools/bin/dump-syms-macos
minidumpmcp/tools/bin/minidump-stackwalk-linux
minidumpmcp/tools/bin/minidump-stackwalk-macos
rust_minidump_mcp-0.1.3.dist-info/METADATA
rust_minidump_mcp-0.1.3.dist-info/WHEEL
rust_minidump_mcp-0.1.3.dist-info/entry_points.txt
rust_minidump_mcp-0.1.3.dist-info/licenses/LICENSE
rust_minidump_mcp-0.1.3.dist-info/RECORD
