Metadata-Version: 2.4
Name: rust-minidump-mcp
Version: 0.1.3
Summary: Rust Minidump MCP server
Project-URL: Homepage, https://github.com/bahamoth/rust-minidump-mcp
Project-URL: Repository, https://github.com/bahamoth/rust-minidump-mcp
Project-URL: Issues, https://github.com/bahamoth/rust-minidump-mcp/issues
Author-email: bahamoth <bahamoth@naver.com>
License-Expression: MIT
License-File: LICENSE
Keywords: crash-analysis,mcp,minidump,rust-minidump
Classifier: Development Status :: 3 - Alpha
Classifier: License :: OSI Approved :: MIT License
Classifier: Programming Language :: Python :: 3
Classifier: Programming Language :: Python :: 3.11
Classifier: Programming Language :: Python :: 3.12
Classifier: Programming Language :: Python :: 3.13
Classifier: Topic :: Software Development :: Debuggers
Classifier: Topic :: Software Development :: Testing
Requires-Python: >=3.13
Requires-Dist: fastmcp>=2.8.1
Requires-Dist: pydantic-settings>=2.9.1
Requires-Dist: pydantic>=2
Requires-Dist: typer>=0.16.0
Requires-Dist: uvicorn
